eth_log/__init__.py
eth_log/example.py
eth_log/run.py
eth_log/utils.py
eth_log/handlers/__init__.py
eth_log/handlers/etherscan_api_handler.py
eth_log/handlers/google_bigquery_handler.py
eth_log/handlers/infura_api_handler.py
eth_log/helpers/__init__.py
eth_log/helpers/eventlog_helper.py
eth_log/models/__init__.py
eth_log/models/contract.py
eth_log/models/eventlog.py
eth_log/models/topic.py
eth_log/models/topic_parser.py
eth_log/tests/__init__.py
eth_log/tests/contract_test.py
eth_log/tests/eventlog_test.py
eth_log/tests/topic_parser_test.py
eth_log/tests/topic_test.py
eth_log-0.3.2.dist-info/DESCRIPTION.rst
eth_log-0.3.2.dist-info/METADATA
eth_log-0.3.2.dist-info/RECORD
eth_log-0.3.2.dist-info/WHEEL
eth_log-0.3.2.dist-info/metadata.json
eth_log-0.3.2.dist-info/top_level.txt
